{
  "热点资讯": [
    {
      "rank": "",
      "title": "中际旭创：一季度净利润57.35亿元，同比增长262.28%",
      "link": "https://news.10jqka.com.cn/20260416/c676048244.shtml",
      "publish_time": "2026-04-16 18:59:00",
      "heat": "7565",
      "type": "热点资讯",
      "crawl_time": "2026-04-16 18:43:48"
    },
    {
      "rank": "",
      "title": "佰维存储：股东孙静等拟合计减持不超2%股份",
      "link": "https://news.10jqka.com.cn/20260416/c676050985.shtml",
      "publish_time": "2026-04-16 19:59:40",
      "heat": "1405",
      "type": "热点资讯",
      "crawl_time": "2026-04-16 18:43:48"
    },
    {
      "rank": "",
      "title": "两部门开展2026年度中央财政支持实施城市更新行动",
      "link": "https://news.10jqka.com.cn/20260416/c676048796.shtml",
      "publish_time": "2026-04-16 19:09:38",
      "heat": "1093",
      "type": "热点资讯",
      "crawl_time": "2026-04-16 18:43:48"
    },
    {
      "rank": "4",
      "title": "贵州茅台：2025年净利润823.2亿元，同比下降4.53%",
      "link": "https://news.10jqka.com.cn/20260416/c676055015.shtml",
      "publish_time": "2026-04-16 22:49:24",
      "heat": "1038",
      "type": "热点资讯",
      "crawl_time": "2026-04-16 18:43:48"
    },
    {
      "rank": "5",
      "title": "美方对伊朗启动代号为“经济狂怒”的行动",
      "link": "https://news.10jqka.com.cn/20260416/c676053229.shtml",
      "publish_time": "2026-04-16 20:45:32",
      "heat": "951",
      "type": "热点资讯",
      "crawl_time": "2026-04-16 18:43:48"
    },
    {
      "rank": "6",
      "title": "晶科科技：就宁夏中卫1GW算力中心项目达成合作意向，项目计划总投资约245亿元",
      "link": "https://news.10jqka.com.cn/20260416/c676047264.shtml",
      "publish_time": "2026-04-16 18:20:19",
      "heat": "737",
      "type": "热点资讯",
      "crawl_time": "2026-04-16 18:43:48"
    },
    {
      "rank": "7",
      "title": "赣锋锂业：预计2026年第一季度净利润为16亿元–21亿元，同比扭亏为盈",
      "link": "https://news.10jqka.com.cn/20260416/c676047428.shtml",
      "publish_time": "2026-04-16 18:25:31",
      "heat": "667",
      "type": "热点资讯",
      "crawl_time": "2026-04-16 18:43:48"
    },
    {
      "rank": "8",
      "title": "特朗普：黎巴嫩与以色列将停火10天",
      "link": "https://news.10jqka.com.cn/20260416/c676055311.shtml",
      "publish_time": "2026-04-16 23:44:02",
      "heat": "591",
      "type": "热点资讯",
      "crawl_time": "2026-04-16 18:43:48"
    },
    {
      "rank": "9",
      "title": "华友钴业：2026年第一季度净利润24.97亿元，同比增长99.45%",
      "link": "https://news.10jqka.com.cn/20260416/c676043519.shtml",
      "publish_time": "2026-04-16 16:42:26",
      "heat": "544",
      "type": "热点资讯",
      "crawl_time": "2026-04-16 18:43:48"
    },
    {
      "rank": "10",
      "title": "贵州茅台2025年财报上市来首次负增长",
      "link": "https://news.10jqka.com.cn/20260416/c676055319.shtml",
      "publish_time": "2026-04-16 23:59:36",
      "heat": "359",
      "type": "热点资讯",
      "crawl_time": "2026-04-16 18:43:48"
    },
    {
      "rank": "11",
      "title": "宏和科技：第一季度净利润1.4亿元，同比增长354.22%",
      "link": "https://news.10jqka.com.cn/20260416/c676045333.shtml",
      "publish_time": "2026-04-16 17:25:23",
      "heat": "278",
      "type": "热点资讯",
      "crawl_time": "2026-04-16 18:43:48"
    },
    {
      "rank": "12",
      "title": "美股开盘：美股三大指数集体高开",
      "link": "https://news.10jqka.com.cn/20260416/c676054060.shtml",
      "publish_time": "2026-04-16 21:31:26",
      "heat": "277",
      "type": "热点资讯",
      "crawl_time": "2026-04-16 18:43:48"
    },
    {
      "rank": "13",
      "title": "外交部：中美就特朗普访华保持着沟通",
      "link": "https://news.10jqka.com.cn/20260416/c676038744.shtml",
      "publish_time": "2026-04-16 15:40:42",
      "heat": "272",
      "type": "热点资讯",
      "crawl_time": "2026-04-16 18:43:48"
    },
    {
      "rank": "14",
      "title": "上交所就晶科科技签署投资协议相关事项发布监管工作函",
      "link": "https://news.10jqka.com.cn/20260416/c676054491.shtml",
      "publish_time": "2026-04-16 21:59:02",
      "heat": "262",
      "type": "热点资讯",
      "crawl_time": "2026-04-16 18:43:48"
    },
    {
      "rank": "15",
      "title": "中际旭创：部分重点客户正在规划 2028 年的需求，有望在 2028 年进一步加大资本开支",
      "link": "https://news.10jqka.com.cn/20260417/c676055461.shtml",
      "publish_time": "2026-04-17 00:16:45",
      "heat": "253",
      "type": "热点资讯",
      "crawl_time": "2026-04-16 18:43:48"
    },
    {
      "rank": "16",
      "title": "“杭州六小龙”之一群核科技港股暗盘一度涨超150%",
      "link": "https://news.10jqka.com.cn/20260416/c676043073.shtml",
      "publish_time": "2026-04-16 16:35:11",
      "heat": "214",
      "type": "热点资讯",
      "crawl_time": "2026-04-16 18:43:48"
    },
    {
      "rank": "17",
      "title": "通富微电：2025年净利润12.19亿元，同比增长79.86%",
      "link": "https://news.10jqka.com.cn/20260416/c676050731.shtml",
      "publish_time": "2026-04-16 19:46:52",
      "heat": "208",
      "type": "热点资讯",
      "crawl_time": "2026-04-16 18:43:48"
    },
    {
      "rank": "18",
      "title": "永辉超市：第一季度净利润2.87亿元，同比增长94.40%",
      "link": "https://news.10jqka.com.cn/20260416/c676050406.shtml",
      "publish_time": "2026-04-16 19:39:55",
      "heat": "195",
      "type": "热点资讯",
      "crawl_time": "2026-04-16 18:43:48"
    },
    {
      "rank": "19",
      "title": "港股新股“AI+光储一体化第一股”思格新能盘中涨超100%",
      "link": "https://news.10jqka.com.cn/20260416/c676038233.shtml",
      "publish_time": "2026-04-16 15:12:09",
      "heat": "186",
      "type": "热点资讯",
      "crawl_time": "2026-04-16 18:43:48"
    },
    {
      "rank": "20",
      "title": "云天化：引入当升科技投建44.93亿元新能源电池材料项目",
      "link": "https://news.10jqka.com.cn/20260416/c676048399.shtml",
      "publish_time": "2026-04-16 18:57:38",
      "heat": "178",
      "type": "热点资讯",
      "crawl_time": "2026-04-16 18:43:48"
    },
    {
      "rank": "21",
      "title": "巴基斯坦外交部：下一轮美伊会谈日期尚未确定",
      "link": "https://news.10jqka.com.cn/20260416/c676039452.shtml",
      "publish_time": "2026-04-16 15:51:54",
      "heat": "153",
      "type": "热点资讯",
      "crawl_time": "2026-04-16 18:43:48"
    },
    {
      "rank": "22",
      "title": "*ST松发：撤销退市风险警示 4月20日复牌简称变更为松发股份",
      "link": "https://news.10jqka.com.cn/20260416/c676050276.shtml",
      "publish_time": "2026-04-16 19:38:29",
      "heat": "140",
      "type": "热点资讯",
      "crawl_time": "2026-04-16 18:43:48"
    },
    {
      "rank": "23",
      "title": "实达集团：预计2025年年度净利润为负值，公司股票可能被实施退市风险警示",
      "link": "https://news.10jqka.com.cn/20260416/c676048415.shtml",
      "publish_time": "2026-04-16 18:54:25",
      "heat": "133",
      "type": "热点资讯",
      "crawl_time": "2026-04-16 18:43:48"
    },
    {
      "rank": "24",
      "title": "国晟科技：公司主营业务及基本面未发生重大变化",
      "link": "https://news.10jqka.com.cn/20260416/c676047793.shtml",
      "publish_time": "2026-04-16 18:36:48",
      "heat": "110",
      "type": "热点资讯",
      "crawl_time": "2026-04-16 18:43:48"
    },
    {
      "rank": "25",
      "title": "标普500期货转跌，此前一度上涨0.3%",
      "link": "https://news.10jqka.com.cn/20260416/c676048243.shtml",
      "publish_time": "2026-04-16 18:50:03",
      "heat": "108",
      "type": "热点资讯",
      "crawl_time": "2026-04-16 18:43:48"
    },
    {
      "rank": "26",
      "title": "台积电CEO：全力扩产仍难以满足强劲AI需求",
      "link": "https://news.10jqka.com.cn/20260416/c676046010.shtml",
      "publish_time": "2026-04-16 17:40:15",
      "heat": "108",
      "type": "热点资讯",
      "crawl_time": "2026-04-16 18:43:48"
    },
    {
      "rank": "27",
      "title": "大族激光：2025年净利润11.9亿元，同比下降29.77%",
      "link": "https://news.10jqka.com.cn/20260416/c676053329.shtml",
      "publish_time": "2026-04-16 20:58:03",
      "heat": "98",
      "type": "热点资讯",
      "crawl_time": "2026-04-16 18:43:48"
    },
    {
      "rank": "28",
      "title": "以色列部长：以总理将与黎巴嫩总统通电话",
      "link": "https://news.10jqka.com.cn/20260416/c676045802.shtml",
      "publish_time": "2026-04-16 17:33:48",
      "heat": "92",
      "type": "热点资讯",
      "crawl_time": "2026-04-16 18:43:48"
    },
    {
      "rank": "29",
      "title": "特朗普说将邀请以黎领导人前往白宫会谈",
      "link": "https://news.10jqka.com.cn/20260417/c676055380.shtml",
      "publish_time": "2026-04-17 00:03:14",
      "heat": "86",
      "type": "热点资讯",
      "crawl_time": "2026-04-16 18:43:48"
    },
    {
      "rank": "30",
      "title": "湖南黄金：预计2026年第一季度净利润同比增长60.00%～90.00%",
      "link": "https://news.10jqka.com.cn/20260416/c676042804.shtml",
      "publish_time": "2026-04-16 16:22:24",
      "heat": "82",
      "type": "热点资讯",
      "crawl_time": "2026-04-16 18:43:48"
    },
    {
      "rank": "31",
      "title": "东方雨虹：第一季度净利润4.02亿元，同比增长108.89%",
      "link": "https://news.10jqka.com.cn/20260416/c676053535.shtml",
      "publish_time": "2026-04-16 20:59:53",
      "heat": "64",
      "type": "热点资讯",
      "crawl_time": "2026-04-16 18:43:48"
    },
    {
      "rank": "32",
      "title": "ST联合：撤销其他风险警示 4月20日起A股简称变更为国旅联合",
      "link": "https://news.10jqka.com.cn/20260416/c676046986.shtml",
      "publish_time": "2026-04-16 18:10:15",
      "heat": "62",
      "type": "热点资讯",
      "crawl_time": "2026-04-16 18:43:48"
    },
    {
      "rank": "33",
      "title": "行云科技：网络上有个别媒体发布的报道不实",
      "link": "https://news.10jqka.com.cn/20260416/c676048590.shtml",
      "publish_time": "2026-04-16 19:00:36",
      "heat": "60",
      "type": "热点资讯",
      "crawl_time": "2026-04-16 18:43:48"
    },
    {
      "rank": "34",
      "title": "黎巴嫩总统：不会与以色列总理通话",
      "link": "https://news.10jqka.com.cn/20260416/c676051002.shtml",
      "publish_time": "2026-04-16 19:58:09",
      "heat": "58",
      "type": "热点资讯",
      "crawl_time": "2026-04-16 18:43:48"
    },
    {
      "rank": "35",
      "title": "神舟二十一号航天员乘组圆满完成第三次出舱活动",
      "link": "https://news.10jqka.com.cn/20260417/c676055681.shtml",
      "publish_time": "2026-04-17 02:05:06",
      "heat": "58",
      "type": "热点资讯",
      "crawl_time": "2026-04-16 18:43:48"
    },
    {
      "rank": "36",
      "title": "东方盛虹：控股股东及一致行动人拟增持9.8亿至19.6亿元",
      "link": "https://news.10jqka.com.cn/20260416/c676045328.shtml",
      "publish_time": "2026-04-16 17:24:46",
      "heat": "57",
      "type": "热点资讯",
      "crawl_time": "2026-04-16 18:43:48"
    },
    {
      "rank": "37",
      "title": "美国上周首次申领失业救济人数为20.7万人；预估为21.3万人",
      "link": "https://news.10jqka.com.cn/20260416/c676051858.shtml",
      "publish_time": "2026-04-16 20:32:35",
      "heat": "50",
      "type": "热点资讯",
      "crawl_time": "2026-04-16 18:43:48"
    },
    {
      "rank": "38",
      "title": "市场监管总局：动态调整CCC认证目录 避免低价低质“内卷式”竞争",
      "link": "https://news.10jqka.com.cn/20260416/c676043066.shtml",
      "publish_time": "2026-04-16 16:35:36",
      "heat": "49",
      "type": "热点资讯",
      "crawl_time": "2026-04-16 18:43:48"
    },
    {
      "rank": "39",
      "title": "以媒：以色列同意停火10天　但不会从黎巴嫩撤军",
      "link": "https://news.10jqka.com.cn/20260417/c676055638.shtml",
      "publish_time": "2026-04-17 01:31:33",
      "heat": "49",
      "type": "热点资讯",
      "crawl_time": "2026-04-16 18:43:48"
    },
    {
      "rank": "40",
      "title": "合盛硅业：2025年净利润亏损29.91亿元",
      "link": "https://news.10jqka.com.cn/20260416/c676050786.shtml",
      "publish_time": "2026-04-16 19:54:30",
      "heat": "46",
      "type": "热点资讯",
      "crawl_time": "2026-04-16 18:43:48"
    },
    {
      "rank": "41",
      "title": "利源股份：公司股票交易可能被实施退市风险警示",
      "link": "https://news.10jqka.com.cn/20260416/c676042762.shtml",
      "publish_time": "2026-04-16 16:22:21",
      "heat": "45",
      "type": "热点资讯",
      "crawl_time": "2026-04-16 18:43:48"
    },
    {
      "rank": "42",
      "title": "3连板*ST观典：股票短期内涨幅较大 明起停牌核查",
      "link": "https://news.10jqka.com.cn/20260416/c676051704.shtml",
      "publish_time": "2026-04-16 20:28:12",
      "heat": "42",
      "type": "热点资讯",
      "crawl_time": "2026-04-16 18:43:48"
    },
    {
      "rank": "43",
      "title": "GQY视讯：公司股票交易可能被实施退市风险警示",
      "link": "https://news.10jqka.com.cn/20260416/c676050727.shtml",
      "publish_time": "2026-04-16 19:47:04",
      "heat": "40",
      "type": "热点资讯",
      "crawl_time": "2026-04-16 18:43:48"
    },
    {
      "rank": "44",
      "title": "富奥股份：2026年第一季度新增订单共85项，预计订单生命周期收入总额167.5亿元",
      "link": "https://news.10jqka.com.cn/20260416/c676043574.shtml",
      "publish_time": "2026-04-16 16:59:37",
      "heat": "30",
      "type": "热点资讯",
      "crawl_time": "2026-04-16 18:43:48"
    },
    {
      "rank": "45",
      "title": "甘肃能化：拟收购金昌化工100%股权 股票复牌",
      "link": "https://news.10jqka.com.cn/20260416/c676051596.shtml",
      "publish_time": "2026-04-16 20:20:56",
      "heat": "29",
      "type": "热点资讯",
      "crawl_time": "2026-04-16 18:43:48"
    },
    {
      "rank": "46",
      "title": "美国总统特朗普表示，应该降低利率",
      "link": "https://news.10jqka.com.cn/20260417/c676055715.shtml",
      "publish_time": "2026-04-17 02:08:47",
      "heat": "29",
      "type": "热点资讯",
      "crawl_time": "2026-04-16 18:43:48"
    },
    {
      "rank": "47",
      "title": "通鼎互联今日涨停，2家机构专用席位净买入1.16亿元",
      "link": "https://news.10jqka.com.cn/20260416/c676042861.shtml",
      "publish_time": "2026-04-16 16:28:13",
      "heat": "28",
      "type": "热点资讯",
      "crawl_time": "2026-04-16 18:43:48"
    },
    {
      "rank": "48",
      "title": "N大普微今日涨430.71%，4家机构专用席位净买入4.22亿元",
      "link": "https://news.10jqka.com.cn/20260416/c676042919.shtml",
      "publish_time": "2026-04-16 16:26:54",
      "heat": "26",
      "type": "热点资讯",
      "crawl_time": "2026-04-16 18:43:48"
    },
    {
      "rank": "49",
      "title": "宏景科技今日20cm涨停，有2家机构专用席位净卖出1.58亿元",
      "link": "https://news.10jqka.com.cn/20260416/c676042841.shtml",
      "publish_time": "2026-04-16 16:27:11",
      "heat": "24",
      "type": "热点资讯",
      "crawl_time": "2026-04-16 18:43:48"
    },
    {
      "rank": "50",
      "title": "特朗普称伊朗同意不拥有核武器 伊方暂无回应",
      "link": "https://news.10jqka.com.cn/20260417/c676055738.shtml",
      "publish_time": "2026-04-17 02:20:25",
      "heat": "22",
      "type": "热点资讯",
      "crawl_time": "2026-04-16 18:43:48"
    },
    {
      "rank": "51",
      "title": "ST泉为：公司股票可能被实施退市风险警示",
      "link": "https://news.10jqka.com.cn/20260416/c676048384.shtml",
      "publish_time": "2026-04-16 18:51:14",
      "heat": "22",
      "type": "热点资讯",
      "crawl_time": "2026-04-16 18:43:48"
    },
    {
      "rank": "52",
      "title": "美股三大指数悉数转涨 费城半导体指数持续拉升",
      "link": "https://news.10jqka.com.cn/20260416/c676055248.shtml",
      "publish_time": "2026-04-16 23:25:27",
      "heat": "19",
      "type": "热点资讯",
      "crawl_time": "2026-04-16 18:43:48"
    },
    {
      "rank": "53",
      "title": "沪硅产业：2025年净亏损15.08亿元",
      "link": "https://news.10jqka.com.cn/20260416/c676053267.shtml",
      "publish_time": "2026-04-16 20:46:19",
      "heat": "18",
      "type": "热点资讯",
      "crawl_time": "2026-04-16 18:43:48"
    },
    {
      "rank": "54",
      "title": "*ST中基：向深圳证券交易所申请撤销退市风险警示",
      "link": "https://news.10jqka.com.cn/20260416/c676055004.shtml",
      "publish_time": "2026-04-16 22:48:03",
      "heat": "14",
      "type": "热点资讯",
      "crawl_time": "2026-04-16 18:43:48"
    },
    {
      "rank": "55",
      "title": "特朗普称美伊可能周末复谈",
      "link": "https://news.10jqka.com.cn/20260417/c676055713.shtml",
      "publish_time": "2026-04-17 02:19:36",
      "heat": "14",
      "type": "热点资讯",
      "crawl_time": "2026-04-16 18:43:48"
    },
    {
      "rank": "56",
      "title": "ST开元：公司股票交易可能被实施退市风险警示",
      "link": "https://news.10jqka.com.cn/20260416/c676043987.shtml",
      "publish_time": "2026-04-16 16:54:02",
      "heat": "11",
      "type": "热点资讯",
      "crawl_time": "2026-04-16 18:43:48"
    },
    {
      "rank": "57",
      "title": "期市夜盘收盘，国内期货主力合约多数上涨，甲醇涨超2%",
      "link": "https://news.10jqka.com.cn/20260416/c676055112.shtml",
      "publish_time": "2026-04-16 23:01:29",
      "heat": "9",
      "type": "热点资讯",
      "crawl_time": "2026-04-16 18:43:48"
    },
    {
      "rank": "58",
      "title": "美国未延长对俄石油制裁豁免 佩斯科夫：已有预期",
      "link": "https://news.10jqka.com.cn/20260416/c676050015.shtml",
      "publish_time": "2026-04-16 19:26:20",
      "heat": "8",
      "type": "热点资讯",
      "crawl_time": "2026-04-16 18:43:48"
    },
    {
      "rank": "59",
      "title": "ETF两市成交额4599.28亿元",
      "link": "https://news.10jqka.com.cn/20260416/c676037858.shtml",
      "publish_time": "2026-04-16 15:01:45",
      "heat": "6",
      "type": "热点资讯",
      "crawl_time": "2026-04-16 18:43:48"
    },
    {
      "rank": "60",
      "title": "期市夜盘开盘，国内期货主力合约多数上涨，甲醇涨超1%",
      "link": "https://news.10jqka.com.cn/20260416/c676053573.shtml",
      "publish_time": "2026-04-16 21:00:45",
      "heat": "4",
      "type": "热点资讯",
      "crawl_time": "2026-04-16 18:43:48"
    },
    {
      "rank": "61",
      "title": "国债期货收盘涨跌互现",
      "link": "https://news.10jqka.com.cn/20260416/c676038620.shtml",
      "publish_time": "2026-04-16 15:16:14",
      "heat": "0",
      "type": "热点资讯",
      "crawl_time": "2026-04-16 18:43:48"
    },
    {
      "rank": "62",
      "title": "*ST铖昌：申请撤销公司股票退市风险警示",
      "link": "https://news.10jqka.com.cn/20260416/c676051677.shtml",
      "publish_time": "2026-04-16 20:25:33",
      "heat": "0",
      "type": "热点资讯",
      "crawl_time": "2026-04-16 18:43:48"
    }
  ],
  "今日热点": [
    {
      "rank": "",
      "title": "工信部：加快打造“创新医药”，合力支持创新药早日生产、上市、进医院",
      "link": "",
      "publish_time": "2026-04-16",
      "heat": "22.8万",
      "type": "今日热点",
      "crawl_time": "2026-04-16 18:43:50"
    },
    {
      "rank": "",
      "title": "特斯拉实现 AI5 芯片流片，股价上涨7.62%",
      "link": "",
      "publish_time": "2026-04-16",
      "heat": "8.7万",
      "type": "今日热点",
      "crawl_time": "2026-04-16 18:43:50"
    },
    {
      "rank": "",
      "title": "中科宇航科创板IPO进入问询阶段",
      "link": "",
      "publish_time": "2026-04-16",
      "heat": "8.1万",
      "type": "今日热点",
      "crawl_time": "2026-04-16 18:43:50"
    },
    {
      "rank": "",
      "title": "全球约六成产能在中国！订单涌来 变压器为何成为外贸“新爆款”？",
      "link": "",
      "publish_time": "2026-04-16",
      "heat": "3.3万",
      "type": "今日热点",
      "crawl_time": "2026-04-16 18:43:50"
    },
    {
      "rank": "",
      "title": "宁德时代AH股双双走强 A股市值突破2万亿元",
      "link": "",
      "publish_time": "2026-04-16",
      "heat": "3.1万",
      "type": "今日热点",
      "crawl_time": "2026-04-16 18:43:50"
    },
    {
      "rank": "",
      "title": "阿里云：对大模型服务平台百炼部分MU（Model Unit）模型单元的服务价格进行上调",
      "link": "",
      "publish_time": "2026-04-16",
      "heat": "1.3万",
      "type": "今日热点",
      "crawl_time": "2026-04-16 18:43:50"
    },
    {
      "rank": "",
      "title": "经国务院同意，国务院办公厅对健全药品价格形成机制提出意见",
      "link": "",
      "publish_time": "2026-04-15",
      "heat": "22.8万",
      "type": "今日热点",
      "crawl_time": "2026-04-16 18:43:50"
    },
    {
      "rank": "",
      "title": "美国联邦通信委员会主席布伦丹·卡尔表示，SpaceX公司已就太空数据中心提出请求",
      "link": "",
      "publish_time": "2026-04-15",
      "heat": "8.1万",
      "type": "今日热点",
      "crawl_time": "2026-04-16 18:43:50"
    },
    {
      "rank": "",
      "title": "亚马逊收购卫星运营商全球星公司",
      "link": "",
      "publish_time": "2026-04-15",
      "heat": "8.1万",
      "type": "今日热点",
      "crawl_time": "2026-04-16 18:43:50"
    },
    {
      "rank": "",
      "title": "燃料电池或成新风口，美股Bloom Energy涨超23% 股价创历史新高",
      "link": "",
      "publish_time": "2026-04-15",
      "heat": "1.4万",
      "type": "今日热点",
      "crawl_time": "2026-04-16 18:43:50"
    },
    {
      "rank": "",
      "title": "英伟达发布全球首个开源量子 AI 模型“ISING”",
      "link": "",
      "publish_time": "2026-04-15",
      "heat": "2838",
      "type": "今日热点",
      "crawl_time": "2026-04-16 18:43:50"
    },
    {
      "rank": "",
      "title": "特朗普称美国对伊朗的战争已经结束",
      "link": "",
      "publish_time": "2026-04-15",
      "heat": "2695",
      "type": "今日热点",
      "crawl_time": "2026-04-16 18:43:50"
    },
    {
      "rank": "",
      "title": "新一代散热材料的重要选项 金刚石散热或迈入产业化应用阶段",
      "link": "",
      "publish_time": "2026-04-15",
      "heat": "2471",
      "type": "今日热点",
      "crawl_time": "2026-04-16 18:43:50"
    },
    {
      "rank": "",
      "title": "苹果智能眼镜据悉已进入密集测试阶段 预计2027年亮相；华为即将发布AI眼镜",
      "link": "",
      "publish_time": "2026-04-14",
      "heat": "5万",
      "type": "今日热点",
      "crawl_time": "2026-04-16 18:43:50"
    },
    {
      "rank": "",
      "title": "中信证券：这一轮电子布涨价弹性及持续性将明显超出市场预期",
      "link": "",
      "publish_time": "2026-04-14",
      "heat": "3.5万",
      "type": "今日热点",
      "crawl_time": "2026-04-16 18:43:50"
    },
    {
      "rank": "",
      "title": "存储芯片巨头股价爆发，一年暴涨2600%",
      "link": "",
      "publish_time": "2026-04-14",
      "heat": "2.3万",
      "type": "今日热点",
      "crawl_time": "2026-04-16 18:43:50"
    },
    {
      "rank": "",
      "title": "算力紧缺 英伟达全系列GPU在云端数据中心的现货租赁价格均大幅上涨",
      "link": "",
      "publish_time": "2026-04-14",
      "heat": "1.3万",
      "type": "今日热点",
      "crawl_time": "2026-04-16 18:43:50"
    },
    {
      "rank": "",
      "title": "机构：近期住房租金阶段性回升",
      "link": "",
      "publish_time": "2026-04-14",
      "heat": "6315",
      "type": "今日热点",
      "crawl_time": "2026-04-16 18:43:50"
    },
    {
      "rank": "",
      "title": "中信证券：XPO将显著扩展可插拔光模块的应用场景",
      "link": "",
      "publish_time": "2026-04-14",
      "heat": "3591",
      "type": "今日热点",
      "crawl_time": "2026-04-16 18:43:50"
    },
    {
      "rank": "",
      "title": "中信建投：国内商业航天即将迎来可回收密集验证窗口",
      "link": "",
      "publish_time": "2026-04-13",
      "heat": "8.1万",
      "type": "今日热点",
      "crawl_time": "2026-04-16 18:43:50"
    },
    {
      "rank": "",
      "title": "两大稀土巨头，涨价！",
      "link": "",
      "publish_time": "2026-04-13",
      "heat": "3.3万",
      "type": "今日热点",
      "crawl_time": "2026-04-16 18:43:50"
    },
    {
      "rank": "",
      "title": "中央台办受权发布 十项促进两岸交流合作的政策措施",
      "link": "",
      "publish_time": "2026-04-13",
      "heat": "7196",
      "type": "今日热点",
      "crawl_time": "2026-04-16 18:43:50"
    },
    {
      "rank": "",
      "title": "光通信巨头产能将售至2028年，CPO概念表现活跃",
      "link": "",
      "publish_time": "2026-04-13",
      "heat": "3591",
      "type": "今日热点",
      "crawl_time": "2026-04-16 18:43:50"
    },
    {
      "rank": "",
      "title": "汇丰、渣打系斩获首批稳定币牌照，香港数字金融基建迎来关键一跃",
      "link": "",
      "publish_time": "2026-04-13",
      "heat": "2810",
      "type": "今日热点",
      "crawl_time": "2026-04-16 18:43:50"
    }
  ],
  "公社热帖": [
    {
      "rank": "",
      "title": "晚间 A股值得关注的资讯",
      "link": "https://www.jiuyangongshe.com/a/2gkp9v15ysn",
      "publish_time": "2026-04-16 21:46:19",
      "heat": "116",
      "type": "公社热帖",
      "crawl_time": "2026-04-16 18:43:52"
    },
    {
      "rank": "",
      "title": "重点关注！今日盘中发酵、信息差、段子！0416",
      "link": "https://www.jiuyangongshe.com/a/4efkh0kmfgl",
      "publish_time": "2026-04-16 16:05:54",
      "heat": "106",
      "type": "公社热帖",
      "crawl_time": "2026-04-16 18:43:52"
    },
    {
      "rank": "",
      "title": "行云科技、润泽科技都拿不到英伟达的卡",
      "link": "https://www.jiuyangongshe.com/a/3xzl9sgun0a",
      "publish_time": "2026-04-16 15:09:25",
      "heat": "104",
      "type": "公社热帖",
      "crawl_time": "2026-04-16 18:43:52"
    },
    {
      "rank": "4",
      "title": "韭研公社学习笔记（260416）",
      "link": "https://www.jiuyangongshe.com/a/2z1n8c1t9bl",
      "publish_time": "2026-04-16 18:56:41",
      "heat": "87",
      "type": "公社热帖",
      "crawl_time": "2026-04-16 18:43:52"
    },
    {
      "rank": "5",
      "title": "4月16日公社内容精选",
      "link": "https://www.jiuyangongshe.com/a/jpshywf5uk",
      "publish_time": "2026-04-16 19:28:50",
      "heat": "62",
      "type": "公社热帖",
      "crawl_time": "2026-04-16 18:43:52"
    },
    {
      "rank": "6",
      "title": "4.16个股信息差（算力爆发）",
      "link": "https://www.jiuyangongshe.com/a/4efkglx3yk6",
      "publish_time": "2026-04-16 15:55:17",
      "heat": "62",
      "type": "公社热帖",
      "crawl_time": "2026-04-16 18:43:52"
    },
    {
      "rank": "7",
      "title": "260416明日看好方向投票",
      "link": "https://www.jiuyangongshe.com/a/3xzlhu5kxp6",
      "publish_time": "2026-04-16 18:35:19",
      "heat": "56",
      "type": "公社热帖",
      "crawl_time": "2026-04-16 18:43:52"
    },
    {
      "rank": "8",
      "title": "底部前瞻，宏景科技一年十倍，全市场年内涨幅第一！",
      "link": "https://www.jiuyangongshe.com/a/3fhm7093umd",
      "publish_time": "2026-04-16 16:11:58",
      "heat": "49",
      "type": "公社热帖",
      "crawl_time": "2026-04-16 18:43:52"
    },
    {
      "rank": "9",
      "title": "新莱应材：台积电洁净室供应商",
      "link": "https://www.jiuyangongshe.com/a/2z1mzkjfw4f",
      "publish_time": "2026-04-16 15:09:02",
      "heat": "43",
      "type": "公社热帖",
      "crawl_time": "2026-04-16 18:43:52"
    },
    {
      "rank": "10",
      "title": "三佳科技：AI算力芯片核心，FoWLP国产破局+合肥国资赋能+特斯拉Terafab铲子股",
      "link": "https://www.jiuyangongshe.com/a/4efkv1bwj09",
      "publish_time": "2026-04-16 21:20:16",
      "heat": "34",
      "type": "公社热帖",
      "crawl_time": "2026-04-16 18:43:52"
    },
    {
      "rank": "11",
      "title": "库存“只有一周多一点” 电子布扩张困于织布机 新产能集中释放要到2027年？",
      "link": "https://www.jiuyangongshe.com/a/1hmql2zgn83",
      "publish_time": "2026-04-16 15:59:32",
      "heat": "34",
      "type": "公社热帖",
      "crawl_time": "2026-04-16 18:43:52"
    },
    {
      "rank": "12",
      "title": "4.16 信息差 (算力正酣、人形曙光)",
      "link": "https://www.jiuyangongshe.com/a/jpsn2vlwr2",
      "publish_time": "2026-04-16 21:16:23",
      "heat": "27",
      "type": "公社热帖",
      "crawl_time": "2026-04-16 18:43:52"
    },
    {
      "rank": "13",
      "title": "全球能源自主叙事下的锂电新机遇论锂电的戴维斯双击!",
      "link": "https://www.jiuyangongshe.com/a/2gkp2jmmq9k",
      "publish_time": "2026-04-16 18:44:37",
      "heat": "25",
      "type": "公社热帖",
      "crawl_time": "2026-04-16 18:43:52"
    },
    {
      "rank": "14",
      "title": "为什么今年算力租赁将远超2023年十倍行情？看懂这3个变量，别再踏空！龙头利润暴增12倍！",
      "link": "https://www.jiuyangongshe.com/a/1hmqvbwsz47",
      "publish_time": "2026-04-16 19:57:32",
      "heat": "23",
      "type": "公社热帖",
      "crawl_time": "2026-04-16 18:43:52"
    },
    {
      "rank": "15",
      "title": "被低估的“算力+云”底座----中青宝",
      "link": "https://www.jiuyangongshe.com/a/203psu3l63s",
      "publish_time": "2026-04-16 16:40:02",
      "heat": "21",
      "type": "公社热帖",
      "crawl_time": "2026-04-16 18:43:52"
    },
    {
      "rank": "16",
      "title": "周四舆情热度（附：图解各热点题材概念）",
      "link": "https://www.jiuyangongshe.com/a/4efkj8g6f5r",
      "publish_time": "2026-04-16 16:35:02",
      "heat": "21",
      "type": "公社热帖",
      "crawl_time": "2026-04-16 18:43:52"
    },
    {
      "rank": "17",
      "title": "2026 年 4 月 16 日连板个股复盘",
      "link": "https://www.jiuyangongshe.com/a/4efkg15zqre",
      "publish_time": "2026-04-16 15:54:13",
      "heat": "19",
      "type": "公社热帖",
      "crawl_time": "2026-04-16 18:43:52"
    },
    {
      "rank": "18",
      "title": "爱施德-正宗低位智算、算力租赁概念股（已有算力订单）+光通信业务",
      "link": "https://www.jiuyangongshe.com/a/4efkl1p5d3z",
      "publish_time": "2026-04-16 17:19:42",
      "heat": "18",
      "type": "公社热帖",
      "crawl_time": "2026-04-16 18:43:52"
    },
    {
      "rank": "19",
      "title": "消息催化挖掘0416",
      "link": "https://www.jiuyangongshe.com/a/2z1n3ble9xk",
      "publish_time": "2026-04-16 16:49:59",
      "heat": "17",
      "type": "公社热帖",
      "crawl_time": "2026-04-16 18:43:52"
    },
    {
      "rank": "20",
      "title": "电子城：硅光+5万P算力+重组预期+量子",
      "link": "https://www.jiuyangongshe.com/a/2z1n8gsb9c0",
      "publish_time": "2026-04-16 19:19:52",
      "heat": "16",
      "type": "公社热帖",
      "crawl_time": "2026-04-16 18:43:52"
    },
    {
      "rank": "21",
      "title": "4月16日复盘笔记：算力租赁/锂电/机器人/燃气轮机/矿产资源/算力硬件/商业航天等",
      "link": "https://www.jiuyangongshe.com/a/203ppmmhdnu",
      "publish_time": "2026-04-16 15:21:45",
      "heat": "16",
      "type": "公社热帖",
      "crawl_time": "2026-04-16 18:43:52"
    },
    {
      "rank": "22",
      "title": "商业航天领航员 长十乙！",
      "link": "https://www.jiuyangongshe.com/a/115rrnseneb",
      "publish_time": "2026-04-16 20:35:00",
      "heat": "15",
      "type": "公社热帖",
      "crawl_time": "2026-04-16 18:43:52"
    },
    {
      "rank": "23",
      "title": "特斯拉机器人迎来爆发机遇，关注其辨识度个股：科森科技",
      "link": "https://www.jiuyangongshe.com/a/3fhmnwl3n3n",
      "publish_time": "2026-04-16 23:02:02",
      "heat": "15",
      "type": "公社热帖",
      "crawl_time": "2026-04-16 18:43:52"
    },
    {
      "rank": "24",
      "title": "陈果：A股牛市要经历三阶段，布局“NAB”三条主线",
      "link": "https://www.jiuyangongshe.com/a/203q03cl03b",
      "publish_time": "2026-04-16 19:47:00",
      "heat": "14",
      "type": "公社热帖",
      "crawl_time": "2026-04-16 18:43:52"
    },
    {
      "rank": "25",
      "title": "“圣阳”一日同风起、扶摇直上九“万里”",
      "link": "https://www.jiuyangongshe.com/a/jpsg00ynwm",
      "publish_time": "2026-04-16 18:44:53",
      "heat": "13",
      "type": "公社热帖",
      "crawl_time": "2026-04-16 18:43:52"
    },
    {
      "rank": "26",
      "title": "4月16日晚间公告",
      "link": "https://www.jiuyangongshe.com/a/jpsq6xtq5p",
      "publish_time": "2026-04-16 22:11:05",
      "heat": "13",
      "type": "公社热帖",
      "crawl_time": "2026-04-16 18:43:52"
    },
    {
      "rank": "27",
      "title": "4.16逻辑梳理",
      "link": "https://www.jiuyangongshe.com/a/203q6s5u9ql",
      "publish_time": "2026-04-16 22:51:40",
      "heat": "13",
      "type": "公社热帖",
      "crawl_time": "2026-04-16 18:43:52"
    },
    {
      "rank": "28",
      "title": "【华福AI互联网】国产算力观点更新",
      "link": "https://www.jiuyangongshe.com/a/115re0zvjet",
      "publish_time": "2026-04-16 15:54:10",
      "heat": "13",
      "type": "公社热帖",
      "crawl_time": "2026-04-16 18:43:52"
    },
    {
      "rank": "29",
      "title": "台积电一季度财报定调CPU重要性，CPU预期差极大！",
      "link": "https://www.jiuyangongshe.com/a/203pskdxszk",
      "publish_time": "2026-04-16 16:35:39",
      "heat": "12",
      "type": "公社热帖",
      "crawl_time": "2026-04-16 18:43:52"
    },
    {
      "rank": "30",
      "title": "坚定积极看好国产算力二季度行情！",
      "link": "https://www.jiuyangongshe.com/a/2z1n3pk0b7a",
      "publish_time": "2026-04-16 16:58:26",
      "heat": "11",
      "type": "公社热帖",
      "crawl_time": "2026-04-16 18:43:52"
    },
    {
      "rank": "31",
      "title": "金禄电子：汽车PCB隐形冠军，布局算力价值重估大幕开启！",
      "link": "https://www.jiuyangongshe.com/a/3xzlj7ml4wb",
      "publish_time": "2026-04-16 18:45:00",
      "heat": "10",
      "type": "公社热帖",
      "crawl_time": "2026-04-16 18:43:52"
    },
    {
      "rank": "32",
      "title": "【能之光】特斯拉AI芯片封测材料核心受益标的，稀缺性凸显！",
      "link": "https://www.jiuyangongshe.com/a/2z1ndtalkeq",
      "publish_time": "2026-04-16 21:16:43",
      "heat": "10",
      "type": "公社热帖",
      "crawl_time": "2026-04-16 18:43:52"
    },
    {
      "rank": "33",
      "title": "晶圆厂扩产大年：半导体洁净室相关厂商梳理",
      "link": "https://www.jiuyangongshe.com/a/jpskz7x35d",
      "publish_time": "2026-04-16 20:27:03",
      "heat": "10",
      "type": "公社热帖",
      "crawl_time": "2026-04-16 18:43:52"
    },
    {
      "rank": "34",
      "title": "4月16日晚间公告精选",
      "link": "https://www.jiuyangongshe.com/a/jpsljb5l9d",
      "publish_time": "2026-04-16 20:38:06",
      "heat": "10",
      "type": "公社热帖",
      "crawl_time": "2026-04-16 18:43:52"
    },
    {
      "rank": "35",
      "title": "东方国信：手握“10万P算力柜+三万卡”的算力基座，央视新闻实锤",
      "link": "https://www.jiuyangongshe.com/a/3fhmlt5u563",
      "publish_time": "2026-04-16 22:07:55",
      "heat": "9",
      "type": "公社热帖",
      "crawl_time": "2026-04-16 18:43:52"
    },
    {
      "rank": "36",
      "title": "0416图表:美国IEEPA关税退款、算力租赁、AI、硫磺、城市更新等",
      "link": "https://www.jiuyangongshe.com/a/2gkpev7p5lr",
      "publish_time": "2026-04-16 23:54:42",
      "heat": "9",
      "type": "公社热帖",
      "crawl_time": "2026-04-16 18:43:52"
    },
    {
      "rank": "37",
      "title": "关注国产算力IOD赛道",
      "link": "https://www.jiuyangongshe.com/a/2gkp3hzed8h",
      "publish_time": "2026-04-16 19:20:30",
      "heat": "8",
      "type": "公社热帖",
      "crawl_time": "2026-04-16 18:43:52"
    },
    {
      "rank": "38",
      "title": "新股大普微：国产企业级SSD核心供应商",
      "link": "https://www.jiuyangongshe.com/a/1hmqpkqu0wh",
      "publish_time": "2026-04-16 17:36:42",
      "heat": "8",
      "type": "公社热帖",
      "crawl_time": "2026-04-16 18:43:52"
    },
    {
      "rank": "39",
      "title": "4月16日A股机构研报部分",
      "link": "https://www.jiuyangongshe.com/a/3fhmlecbkyt",
      "publish_time": "2026-04-16 21:58:42",
      "heat": "8",
      "type": "公社热帖",
      "crawl_time": "2026-04-16 18:43:52"
    },
    {
      "rank": "40",
      "title": "量子科技：风口之上的产业跃迁与投资机遇",
      "link": "https://www.jiuyangongshe.com/a/jpsnt6bkb1",
      "publish_time": "2026-04-16 21:37:49",
      "heat": "7",
      "type": "公社热帖",
      "crawl_time": "2026-04-16 18:43:52"
    },
    {
      "rank": "41",
      "title": "中嘉博创：是有逻辑的！",
      "link": "https://www.jiuyangongshe.com/a/2z1nhbk7a6j",
      "publish_time": "2026-04-16 23:10:22",
      "heat": "7",
      "type": "公社热帖",
      "crawl_time": "2026-04-16 18:43:52"
    },
    {
      "rank": "42",
      "title": "机器人量产前夕，强烈推荐进攻核心组合！",
      "link": "https://www.jiuyangongshe.com/a/3fhmhpzb3d5",
      "publish_time": "2026-04-16 20:44:00",
      "heat": "7",
      "type": "公社热帖",
      "crawl_time": "2026-04-16 18:43:52"
    },
    {
      "rank": "43",
      "title": "锐少复盘-2026年4月16日（明日继续震荡？）",
      "link": "https://www.jiuyangongshe.com/a/2gkpa8f1fwv",
      "publish_time": "2026-04-16 21:58:56",
      "heat": "7",
      "type": "公社热帖",
      "crawl_time": "2026-04-16 18:43:52"
    },
    {
      "rank": "44",
      "title": "4月17日盘前必读……马斯克宣布特斯拉实现AI5芯片流片！",
      "link": "https://www.jiuyangongshe.com/a/jpslmqvmuv",
      "publish_time": "2026-04-16 20:41:28",
      "heat": "7",
      "type": "公社热帖",
      "crawl_time": "2026-04-16 18:43:52"
    },
    {
      "rank": "45",
      "title": "☄☄☄【未知来源】#解答当前市场对于燃机和sofc的几点分歧",
      "link": "https://www.jiuyangongshe.com/a/jpsa5a2pe1",
      "publish_time": "2026-04-16 16:11:30",
      "heat": "7",
      "type": "公社热帖",
      "crawl_time": "2026-04-16 18:43:52"
    },
    {
      "rank": "46",
      "title": "AI算力板块疯狂涨停潮：实达集团600734作为福建大数据集团唯一上市公司聚焦算力核心业务",
      "link": "https://www.jiuyangongshe.com/a/3fhmd1ag27b",
      "publish_time": "2026-04-16 18:45:02",
      "heat": "6",
      "type": "公社热帖",
      "crawl_time": "2026-04-16 18:43:52"
    },
    {
      "rank": "47",
      "title": "【天风电新】晶科科技：耐心等待中卫算电协同，政策强催化下价值重估正当时",
      "link": "https://www.jiuyangongshe.com/a/4efkfl6fgkr",
      "publish_time": "2026-04-16 15:24:48",
      "heat": "6",
      "type": "公社热帖",
      "crawl_time": "2026-04-16 18:43:52"
    },
    {
      "rank": "48",
      "title": "大普微：剑指5000亿史诗级逻辑推演！全栈自研绝对统治力，技术段位碾压沐曦摩尔！",
      "link": "https://www.jiuyangongshe.com/a/115rw8wehv5",
      "publish_time": "2026-04-16 22:32:59",
      "heat": "6",
      "type": "公社热帖",
      "crawl_time": "2026-04-16 18:43:52"
    },
    {
      "rank": "49",
      "title": "【国泰海通医药】奥锐特2025年业绩",
      "link": "https://www.jiuyangongshe.com/a/jpsjbvqwsp",
      "publish_time": "2026-04-16 19:46:28",
      "heat": "6",
      "type": "公社热帖",
      "crawl_time": "2026-04-16 18:43:52"
    },
    {
      "rank": "50",
      "title": "光模块都新高了，PCB会不会跟上？",
      "link": "https://www.jiuyangongshe.com/a/203q4hpw5n8",
      "publish_time": "2026-04-16 21:46:08",
      "heat": "6",
      "type": "公社热帖",
      "crawl_time": "2026-04-16 18:43:52"
    },
    {
      "rank": "51",
      "title": "机构观点：为什么一定要重视硅光。",
      "link": "https://www.jiuyangongshe.com/a/115rdbc93f9",
      "publish_time": "2026-04-16 15:19:56",
      "heat": "6",
      "type": "公社热帖",
      "crawl_time": "2026-04-16 18:43:52"
    },
    {
      "rank": "52",
      "title": "光芯片紧缺：中际旭创业绩超预期，上游材料预付款暴增10倍",
      "link": "https://www.jiuyangongshe.com/a/1hmr290dfmb",
      "publish_time": "2026-04-16 23:01:50",
      "heat": "6",
      "type": "公社热帖",
      "crawl_time": "2026-04-16 18:43:52"
    },
    {
      "rank": "53",
      "title": "宁德时代业绩超预期引爆板块！干法电极是最大赢家",
      "link": "https://www.jiuyangongshe.com/a/3xzlmg3219u",
      "publish_time": "2026-04-16 20:09:27",
      "heat": "6",
      "type": "公社热帖",
      "crawl_time": "2026-04-16 18:43:52"
    },
    {
      "rank": "54",
      "title": "20260416复盘：AI硬件再被财报“实锤”，指数放量上攻，但短线合力仍主要集中在算力链",
      "link": "https://www.jiuyangongshe.com/a/203q1g6leat",
      "publish_time": "2026-04-16 20:31:37",
      "heat": "6",
      "type": "公社热帖",
      "crawl_time": "2026-04-16 18:43:52"
    },
    {
      "rank": "55",
      "title": "4.16晚间重要公告梳理",
      "link": "https://www.jiuyangongshe.com/a/3xzlsyzvmnj",
      "publish_time": "2026-04-16 22:35:40",
      "heat": "6",
      "type": "公社热帖",
      "crawl_time": "2026-04-16 18:43:52"
    },
    {
      "rank": "56",
      "title": "全网唯一百亿以下800G光模块上市公司",
      "link": "https://www.jiuyangongshe.com/a/4efkwtvtu1w",
      "publish_time": "2026-04-16 21:59:13",
      "heat": "5",
      "type": "公社热帖",
      "crawl_time": "2026-04-16 18:43:52"
    },
    {
      "rank": "57",
      "title": "[上海 计算机] 从“十五五”规划看未来产业——量子“跃迁”、人机“融合”",
      "link": "https://www.jiuyangongshe.com/a/2gkp2ek0g1r",
      "publish_time": "2026-04-16 18:44:17",
      "heat": "5",
      "type": "公社热帖",
      "crawl_time": "2026-04-16 18:43:52"
    },
    {
      "rank": "58",
      "title": "【国泰海通商社】继续推荐景区：政策推动、供求双旺，景区板块迎黄金投资期",
      "link": "https://www.jiuyangongshe.com/a/4efkentjng4",
      "publish_time": "2026-04-16 15:02:27",
      "heat": "5",
      "type": "公社热帖",
      "crawl_time": "2026-04-16 18:43:52"
    },
    {
      "rank": "59",
      "title": "AI算力软件/机器人/商业航天",
      "link": "https://www.jiuyangongshe.com/a/115rnvdv2pt",
      "publish_time": "2026-04-16 19:22:32",
      "heat": "5",
      "type": "公社热帖",
      "crawl_time": "2026-04-16 18:43:52"
    },
    {
      "rank": "60",
      "title": "洁净室",
      "link": "https://www.jiuyangongshe.com/a/2z1n6sw5phr",
      "publish_time": "2026-04-16 18:19:23",
      "heat": "5",
      "type": "公社热帖",
      "crawl_time": "2026-04-16 18:43:52"
    },
    {
      "rank": "61",
      "title": "4.17三大报内参",
      "link": "https://www.jiuyangongshe.com/a/jpsqwjtdz5",
      "publish_time": "2026-04-16 22:39:27",
      "heat": "5",
      "type": "公社热帖",
      "crawl_time": "2026-04-16 18:43:52"
    },
    {
      "rank": "62",
      "title": "20260416今日段子汇总",
      "link": "https://www.jiuyangongshe.com/a/2z1nffc5db2",
      "publish_time": "2026-04-16 21:59:23",
      "heat": "4",
      "type": "公社热帖",
      "crawl_time": "2026-04-16 18:43:52"
    },
    {
      "rank": "63",
      "title": "商业航天即将开启第二波",
      "link": "https://www.jiuyangongshe.com/a/3xzlt751m8r",
      "publish_time": "2026-04-16 22:38:23",
      "heat": "4",
      "type": "公社热帖",
      "crawl_time": "2026-04-16 18:43:52"
    },
    {
      "rank": "64",
      "title": "星辰大海再提速：商业航天概念持续爆发背后的逻辑与机遇",
      "link": "https://www.jiuyangongshe.com/a/jpsf0rept0",
      "publish_time": "2026-04-16 18:13:35",
      "heat": "4",
      "type": "公社热帖",
      "crawl_time": "2026-04-16 18:43:52"
    },
    {
      "rank": "65",
      "title": "[东吴 环保] 再探环卫无人化，持筹握剑指成本",
      "link": "https://www.jiuyangongshe.com/a/115rj883nqj",
      "publish_time": "2026-04-16 17:24:00",
      "heat": "4",
      "type": "公社热帖",
      "crawl_time": "2026-04-16 18:43:52"
    },
    {
      "rank": "66",
      "title": "【中信电新】晶科科技投资建设1GW算力中心项目，重视“算电协同”核心标的",
      "link": "https://www.jiuyangongshe.com/a/3fhmdtxkm8r",
      "publish_time": "2026-04-16 19:20:42",
      "heat": "4",
      "type": "公社热帖",
      "crawl_time": "2026-04-16 18:43:52"
    },
    {
      "rank": "67",
      "title": "【中泰传媒互联网】腾讯/阿里世界模型发布，AI交互技术落地加速产业变革",
      "link": "https://www.jiuyangongshe.com/a/2gkp5zfx43h",
      "publish_time": "2026-04-16 20:09:00",
      "heat": "4",
      "type": "公社热帖",
      "crawl_time": "2026-04-16 18:43:52"
    },
    {
      "rank": "68",
      "title": "华策影视算力业务2026年发展规模",
      "link": "https://www.jiuyangongshe.com/a/3xzljayugml",
      "publish_time": "2026-04-16 18:51:15",
      "heat": "4",
      "type": "公社热帖",
      "crawl_time": "2026-04-16 18:43:52"
    },
    {
      "rank": "69",
      "title": "盘面+资讯+研报梳理",
      "link": "https://www.jiuyangongshe.com/a/115rxff51j2",
      "publish_time": "2026-04-16 23:06:00",
      "heat": "4",
      "type": "公社热帖",
      "crawl_time": "2026-04-16 18:43:52"
    },
    {
      "rank": "70",
      "title": "英伟达引爆量子AI！神州信息：量子基建龙头+业绩翻倍，主升浪启动",
      "link": "https://www.jiuyangongshe.com/a/2z1n52thzmx",
      "publish_time": "2026-04-16 17:37:03",
      "heat": "4",
      "type": "公社热帖",
      "crawl_time": "2026-04-16 18:43:52"
    },
    {
      "rank": "71",
      "title": "SpaceX：重构万亿太空基建，定义下一代全球基础设施",
      "link": "https://www.jiuyangongshe.com/a/3xzlrf601j6",
      "publish_time": "2026-04-16 21:56:45",
      "heat": "4",
      "type": "公社热帖",
      "crawl_time": "2026-04-16 18:43:52"
    },
    {
      "rank": "72",
      "title": "【DW】九丰能源：重视资源价值，国产氦气核心供应商",
      "link": "https://www.jiuyangongshe.com/a/2z1n3be7kgk",
      "publish_time": "2026-04-16 16:45:54",
      "heat": "4",
      "type": "公社热帖",
      "crawl_time": "2026-04-16 18:43:52"
    },
    {
      "rank": "73",
      "title": "【HT】农林牧渔行业动态点评：生猪产能去化大幕已开启",
      "link": "https://www.jiuyangongshe.com/a/2z1mzu20mbr",
      "publish_time": "2026-04-16 15:19:53",
      "heat": "4",
      "type": "公社热帖",
      "crawl_time": "2026-04-16 18:43:52"
    },
    {
      "rank": "74",
      "title": "中恒电气：宁王为何溢价45%收购？",
      "link": "https://www.jiuyangongshe.com/a/2gkpe5tef6r",
      "publish_time": "2026-04-16 23:37:02",
      "heat": "3",
      "type": "公社热帖",
      "crawl_time": "2026-04-16 18:43:52"
    },
    {
      "rank": "75",
      "title": "中际旭创2026Q1交流",
      "link": "https://www.jiuyangongshe.com/a/jpsssk07ht",
      "publish_time": "2026-04-16 23:39:46",
      "heat": "3",
      "type": "公社热帖",
      "crawl_time": "2026-04-16 18:43:52"
    },
    {
      "rank": "76",
      "title": "全球算力涨价潮、国产集群落地",
      "link": "https://www.jiuyangongshe.com/a/1hmqzsbm83a",
      "publish_time": "2026-04-16 21:58:29",
      "heat": "3",
      "type": "公社热帖",
      "crawl_time": "2026-04-16 18:43:52"
    },
    {
      "rank": "77",
      "title": "新股埃泰克：车身域控制器龙头企业",
      "link": "https://www.jiuyangongshe.com/a/203puter3y8",
      "publish_time": "2026-04-16 17:36:49",
      "heat": "3",
      "type": "公社热帖",
      "crawl_time": "2026-04-16 18:43:52"
    },
    {
      "rank": "78",
      "title": "算力租赁低位票，深挖一下",
      "link": "https://www.jiuyangongshe.com/a/3fhmkq0z8an",
      "publish_time": "2026-04-16 21:45:15",
      "heat": "3",
      "type": "公社热帖",
      "crawl_time": "2026-04-16 18:43:52"
    },
    {
      "rank": "79",
      "title": "【zx机械】继续坚定看好中国动力20260416",
      "link": "https://www.jiuyangongshe.com/a/3fhmcfqn4j9",
      "publish_time": "2026-04-16 18:29:43",
      "heat": "3",
      "type": "公社热帖",
      "crawl_time": "2026-04-16 18:43:52"
    },
    {
      "rank": "80",
      "title": "【华源电子】重视芯片测试产业链的通胀效应",
      "link": "https://www.jiuyangongshe.com/a/4efkjdrfn02",
      "publish_time": "2026-04-16 16:37:00",
      "heat": "3",
      "type": "公社热帖",
      "crawl_time": "2026-04-16 18:43:52"
    },
    {
      "rank": "81",
      "title": "【浙商传媒互联网】完美世界4月16日公布最新《异环》公测玩法PV",
      "link": "https://www.jiuyangongshe.com/a/4efkewsgb0p",
      "publish_time": "2026-04-16 15:09:44",
      "heat": "3",
      "type": "公社热帖",
      "crawl_time": "2026-04-16 18:43:52"
    },
    {
      "rank": "82",
      "title": "【申万计算机】国产AI算力链继续推荐！260416",
      "link": "https://www.jiuyangongshe.com/a/2gkny86h92v",
      "publish_time": "2026-04-16 16:50:14",
      "heat": "3",
      "type": "公社热帖",
      "crawl_time": "2026-04-16 18:43:52"
    },
    {
      "rank": "83",
      "title": "[国信 医药生物] AACR会议召开在即，建议关注具备创新资产的公司",
      "link": "https://www.jiuyangongshe.com/a/2z1ng07fy0j",
      "publish_time": "2026-04-16 22:12:02",
      "heat": "3",
      "type": "公社热帖",
      "crawl_time": "2026-04-16 18:43:52"
    },
    {
      "rank": "84",
      "title": "云厂集体涨价落地！算力板块业绩暴增，抱团格局不变",
      "link": "https://www.jiuyangongshe.com/a/2gkp9lw5pab",
      "publish_time": "2026-04-16 21:45:45",
      "heat": "2",
      "type": "公社热帖",
      "crawl_time": "2026-04-16 18:43:52"
    },
    {
      "rank": "85",
      "title": "全世界都被比亚迪包围了？",
      "link": "https://www.jiuyangongshe.com/a/2z1n88qukbq",
      "publish_time": "2026-04-16 18:56:55",
      "heat": "2",
      "type": "公社热帖",
      "crawl_time": "2026-04-16 18:43:52"
    },
    {
      "rank": "86",
      "title": "大趋势机会晚报汇总",
      "link": "https://www.jiuyangongshe.com/a/115rxg7a3af",
      "publish_time": "2026-04-16 23:04:34",
      "heat": "2",
      "type": "公社热帖",
      "crawl_time": "2026-04-16 18:43:52"
    },
    {
      "rank": "87",
      "title": "天润工业：主业稳健，曲轴连杆深度拥抱AIDC，ASP+份额向",
      "link": "https://www.jiuyangongshe.com/a/jpsgvjsq54",
      "publish_time": "2026-04-16 19:20:09",
      "heat": "2",
      "type": "公社热帖",
      "crawl_time": "2026-04-16 18:43:52"
    },
    {
      "rank": "88",
      "title": "尿素内外价差超3倍 国内龙头企业迎来历史性机遇",
      "link": "https://www.jiuyangongshe.com/a/2z1neh441a3",
      "publish_time": "2026-04-16 21:34:00",
      "heat": "2",
      "type": "公社热帖",
      "crawl_time": "2026-04-16 18:43:52"
    },
    {
      "rank": "89",
      "title": "脱水研报、评级、强势20260416",
      "link": "https://www.jiuyangongshe.com/a/jpsq0p0bjn",
      "publish_time": "2026-04-16 22:05:01",
      "heat": "2",
      "type": "公社热帖",
      "crawl_time": "2026-04-16 18:43:52"
    },
    {
      "rank": "90",
      "title": "【长城电新 |】储能观点再更新：海外市场高景气度全面确认",
      "link": "https://www.jiuyangongshe.com/a/115rdnjs8pn",
      "publish_time": "2026-04-16 15:32:36",
      "heat": "2",
      "type": "公社热帖",
      "crawl_time": "2026-04-16 18:43:52"
    },
    {
      "rank": "91",
      "title": "东阳光 受益中际旭创业绩预期差",
      "link": "https://www.jiuyangongshe.com/a/1hmqj6vzdkn",
      "publish_time": "2026-04-16 15:10:01",
      "heat": "2",
      "type": "公社热帖",
      "crawl_time": "2026-04-16 18:43:52"
    },
    {
      "rank": "92",
      "title": "百邦科技：最低估的算力股，手握2万P对标200亿估值，10倍潜力！",
      "link": "https://www.jiuyangongshe.com/a/115ry6kc183",
      "publish_time": "2026-04-16 23:23:01",
      "heat": "2",
      "type": "公社热帖",
      "crawl_time": "2026-04-16 18:43:52"
    },
    {
      "rank": "93",
      "title": "4.16新闻联播（附详情）",
      "link": "https://www.jiuyangongshe.com/a/203q225yy30",
      "publish_time": "2026-04-16 20:41:35",
      "heat": "2",
      "type": "公社热帖",
      "crawl_time": "2026-04-16 18:43:52"
    },
    {
      "rank": "94",
      "title": "4.16题材",
      "link": "https://www.jiuyangongshe.com/a/203q481hgze",
      "publish_time": "2026-04-16 21:44:43",
      "heat": "2",
      "type": "公社热帖",
      "crawl_time": "2026-04-16 18:43:52"
    },
    {
      "rank": "95",
      "title": "[国金 电新] 欧洲海风：订单放量信号明显，能源安全驱动长期需求确定性提升",
      "link": "https://www.jiuyangongshe.com/a/4efky3uy06p",
      "publish_time": "2026-04-16 22:30:06",
      "heat": "2",
      "type": "公社热帖",
      "crawl_time": "2026-04-16 18:43:52"
    },
    {
      "rank": "96",
      "title": "【东吴机械】浙江鼎力：2025年报快评",
      "link": "https://www.jiuyangongshe.com/a/115rnxqmjzz",
      "publish_time": "2026-04-16 19:28:27",
      "heat": "2",
      "type": "公社热帖",
      "crawl_time": "2026-04-16 18:43:52"
    },
    {
      "rank": "97",
      "title": "【中信证券前瞻】台积电（TSM）26Q1法说会概要",
      "link": "https://www.jiuyangongshe.com/a/115rf7uzqtu",
      "publish_time": "2026-04-16 16:06:27",
      "heat": "2",
      "type": "公社热帖",
      "crawl_time": "2026-04-16 18:43:52"
    },
    {
      "rank": "98",
      "title": "【中信通信】旭创26Q1业绩超预期",
      "link": "https://www.jiuyangongshe.com/a/115rnzeh0pm",
      "publish_time": "2026-04-16 19:28:38",
      "heat": "2",
      "type": "公社热帖",
      "crawl_time": "2026-04-16 18:43:52"
    },
    {
      "rank": "99",
      "title": "【中泰电子丨台积电】26Q1营收超预期，全年资本开支预计接近指引上限",
      "link": "https://www.jiuyangongshe.com/a/3xzlhmytqy3",
      "publish_time": "2026-04-16 18:29:55",
      "heat": "2",
      "type": "公社热帖",
      "crawl_time": "2026-04-16 18:43:52"
    },
    {
      "rank": "100",
      "title": "【凌玮科技】董事长交流心得：进一步坚定信心，更新推荐【东北计",
      "link": "https://www.jiuyangongshe.com/a/2gkpae00c4a",
      "publish_time": "2026-04-16 22:00:01",
      "heat": "2",
      "type": "公社热帖",
      "crawl_time": "2026-04-16 18:43:52"
    },
    {
      "rank": "101",
      "title": "【国金金属材料】锂矿板块：迎接全球电动化下新一轮的上行大周期！",
      "link": "https://www.jiuyangongshe.com/a/jpsbdynst4",
      "publish_time": "2026-04-16 16:44:44",
      "heat": "2",
      "type": "公社热帖",
      "crawl_time": "2026-04-16 18:43:52"
    },
    {
      "rank": "102",
      "title": "【天风电新】晶科科技：耐心等待中卫算电协同，政策强催化下价值重估正当时",
      "link": "https://www.jiuyangongshe.com/a/115rdedjcjb",
      "publish_time": "2026-04-16 15:20:02",
      "heat": "2",
      "type": "公社热帖",
      "crawl_time": "2026-04-16 18:43:52"
    },
    {
      "rank": "103",
      "title": "个股分析之云南白药",
      "link": "https://www.jiuyangongshe.com/a/2z1nhr4ez6k",
      "publish_time": "2026-04-16 22:57:02",
      "heat": "2",
      "type": "公社热帖",
      "crawl_time": "2026-04-16 18:43:52"
    },
    {
      "rank": "104",
      "title": "中泰机械 | 泰坦股份】AI 驱动电子布结构性缺口，电子布织机为核心卡点",
      "link": "https://www.jiuyangongshe.com/a/4efkzj0a8yd",
      "publish_time": "2026-04-17 01:25:39",
      "heat": "1",
      "type": "公社热帖",
      "crawl_time": "2026-04-16 18:43:52"
    },
    {
      "rank": "105",
      "title": "五一消费大超预期",
      "link": "https://www.jiuyangongshe.com/a/4efkx9rmz7t",
      "publish_time": "2026-04-16 22:15:30",
      "heat": "1",
      "type": "公社热帖",
      "crawl_time": "2026-04-16 18:43:52"
    },
    {
      "rank": "106",
      "title": "光学与先进封装：核心工艺设备供需格局",
      "link": "https://www.jiuyangongshe.com/a/2z1n3metru4",
      "publish_time": "2026-04-16 16:54:27",
      "heat": "1",
      "type": "公社热帖",
      "crawl_time": "2026-04-16 18:43:52"
    },
    {
      "rank": "107",
      "title": "动力电池导热胶：技术突破、市场格局与产业链重构的深度洞察",
      "link": "https://www.jiuyangongshe.com/a/203praf42lw",
      "publish_time": "2026-04-16 16:03:17",
      "heat": "1",
      "type": "公社热帖",
      "crawl_time": "2026-04-16 18:43:52"
    },
    {
      "rank": "108",
      "title": "博迁新材（605376）AI+新能源双赛道镍龙头",
      "link": "https://www.jiuyangongshe.com/a/2gknw4zgspz",
      "publish_time": "2026-04-16 15:53:02",
      "heat": "1",
      "type": "公社热帖",
      "crawl_time": "2026-04-16 18:43:52"
    },
    {
      "rank": "109",
      "title": "变压器超级周期-产业趋势和机会",
      "link": "https://www.jiuyangongshe.com/a/2gknvlj1x0s",
      "publish_time": "2026-04-16 15:46:48",
      "heat": "1",
      "type": "公社热帖",
      "crawl_time": "2026-04-16 18:43:52"
    },
    {
      "rank": "110",
      "title": "周四财经消息汇总  2026-4-16",
      "link": "https://www.jiuyangongshe.com/a/2gkpelvbkzc",
      "publish_time": "2026-04-16 23:56:33",
      "heat": "1",
      "type": "公社热帖",
      "crawl_time": "2026-04-16 18:43:52"
    },
    {
      "rank": "111",
      "title": "实时美股涨幅榜",
      "link": "https://www.jiuyangongshe.com/a/1hmr1tfs4e4",
      "publish_time": "2026-04-16 22:51:12",
      "heat": "1",
      "type": "公社热帖",
      "crawl_time": "2026-04-16 18:43:52"
    },
    {
      "rank": "112",
      "title": "每日知讯 4.16",
      "link": "https://www.jiuyangongshe.com/a/3xzld5g5gp5",
      "publish_time": "2026-04-16 16:34:04",
      "heat": "1",
      "type": "公社热帖",
      "crawl_time": "2026-04-16 18:43:52"
    },
    {
      "rank": "113",
      "title": "每日研究一家上市公司——第135家奋达科技（深圳）",
      "link": "https://www.jiuyangongshe.com/a/jpsf2xdlex",
      "publish_time": "2026-04-16 18:14:19",
      "heat": "1",
      "type": "公社热帖",
      "crawl_time": "2026-04-16 18:43:52"
    },
    {
      "rank": "114",
      "title": "涪陵电力：转型的开始",
      "link": "https://www.jiuyangongshe.com/a/3xzlv514992",
      "publish_time": "2026-04-16 23:26:00",
      "heat": "1",
      "type": "公社热帖",
      "crawl_time": "2026-04-16 18:43:52"
    },
    {
      "rank": "115",
      "title": "稀土管制升级，供需失衡持续演绎，价格上涨预期强烈，重塑全球供应体系，稀土概念股全梳理",
      "link": "https://www.jiuyangongshe.com/a/2gkp8fcztru",
      "publish_time": "2026-04-16 21:15:59",
      "heat": "1",
      "type": "公社热帖",
      "crawl_time": "2026-04-16 18:43:52"
    },
    {
      "rank": "116",
      "title": "第十四届中国数控机床展览会（CCMT2026）即将召开，核心概念股梳理",
      "link": "https://www.jiuyangongshe.com/a/1hmr5fr3eew",
      "publish_time": "2026-04-17 00:26:14",
      "heat": "1",
      "type": "公社热帖",
      "crawl_time": "2026-04-16 18:43:52"
    },
    {
      "rank": "117",
      "title": "算力租赁",
      "link": "https://www.jiuyangongshe.com/a/2z1nnz1bkuq",
      "publish_time": "2026-04-17 01:12:01",
      "heat": "1",
      "type": "公社热帖",
      "crawl_time": "2026-04-16 18:43:52"
    },
    {
      "rank": "118",
      "title": "算力租赁产业链核心赛道全解析",
      "link": "https://www.jiuyangongshe.com/a/4efks3rbn4b",
      "publish_time": "2026-04-16 19:56:26",
      "heat": "1",
      "type": "公社热帖",
      "crawl_time": "2026-04-16 18:43:52"
    },
    {
      "rank": "119",
      "title": "道通科技：锚定能源革命与AI创新，多维布局打开成长空间",
      "link": "https://www.jiuyangongshe.com/a/jps8ja7nl8",
      "publish_time": "2026-04-16 15:26:37",
      "heat": "1",
      "type": "公社热帖",
      "crawl_time": "2026-04-16 18:43:52"
    },
    {
      "rank": "120",
      "title": "陕西旅游盛装登场",
      "link": "https://www.jiuyangongshe.com/a/3fhmm4dtknh",
      "publish_time": "2026-04-16 22:20:39",
      "heat": "1",
      "type": "公社热帖",
      "crawl_time": "2026-04-16 18:43:52"
    },
    {
      "rank": "121",
      "title": "雷科防务（002413）核心技术优势分析",
      "link": "https://www.jiuyangongshe.com/a/2gkphzphasa",
      "publish_time": "2026-04-17 01:16:03",
      "heat": "1",
      "type": "公社热帖",
      "crawl_time": "2026-04-16 18:43:52"
    },
    {
      "rank": "122",
      "title": "04月16评级日报 强势股脱水 脱水研报",
      "link": "https://www.jiuyangongshe.com/a/jpsmlhw3a4",
      "publish_time": "2026-04-16 21:02:01",
      "heat": "1",
      "type": "公社热帖",
      "crawl_time": "2026-04-16 18:43:52"
    },
    {
      "rank": "123",
      "title": "2025-2026年中国猪肉价格走势与头部猪企财务深度研究报",
      "link": "https://www.jiuyangongshe.com/a/4efl1hd2cz0",
      "publish_time": "2026-04-16 23:58:01",
      "heat": "1",
      "type": "公社热帖",
      "crawl_time": "2026-04-16 18:43:52"
    },
    {
      "rank": "124",
      "title": "HW950服务器，DeepSeek V4催化下的算力新主线",
      "link": "https://www.jiuyangongshe.com/a/3fhms0ene8g",
      "publish_time": "2026-04-17 00:26:17",
      "heat": "1",
      "type": "公社热帖",
      "crawl_time": "2026-04-16 18:43:52"
    },
    {
      "rank": "125",
      "title": "[国信 策略] 假期接踵助力社会服务行业景气修复，继续看好优质细分龙头",
      "link": "https://www.jiuyangongshe.com/a/2z1nfq5w9ef",
      "publish_time": "2026-04-16 22:06:56",
      "heat": "1",
      "type": "公社热帖",
      "crawl_time": "2026-04-16 18:43:52"
    },
    {
      "rank": "126",
      "title": "❗️【天风电新】IEEPA退款启动临近，继续看好出口链涛涛、春风、隆鑫",
      "link": "https://www.jiuyangongshe.com/a/jps86svq9d",
      "publish_time": "2026-04-16 15:19:59",
      "heat": "1",
      "type": "公社热帖",
      "crawl_time": "2026-04-16 18:43:52"
    },
    {
      "rank": "127",
      "title": "【中信传媒】三七互娱2025年年报点评",
      "link": "https://www.jiuyangongshe.com/a/203pxrjdcdc",
      "publish_time": "2026-04-16 18:50:58",
      "heat": "1",
      "type": "公社热帖",
      "crawl_time": "2026-04-16 18:43:52"
    },
    {
      "rank": "128",
      "title": "【华创化工】赛轮轮胎：非公路业务持续突破，全球化与高端化同步推进",
      "link": "https://www.jiuyangongshe.com/a/3fhm4syp2w9",
      "publish_time": "2026-04-16 15:11:00",
      "heat": "1",
      "type": "公社热帖",
      "crawl_time": "2026-04-16 18:43:52"
    },
    {
      "rank": "129",
      "title": "【国联民生海外】空头回补与产业利好共振，美股科技巨头迎来大反弹❗️",
      "link": "https://www.jiuyangongshe.com/a/115rj0sldky",
      "publish_time": "2026-04-16 17:18:22",
      "heat": "1",
      "type": "公社热帖",
      "crawl_time": "2026-04-16 18:43:52"
    },
    {
      "rank": "130",
      "title": "【未知来源】奕瑞科技：26Q1业绩前瞻-基本面复盘(增速指收入端)：",
      "link": "https://www.jiuyangongshe.com/a/4efkha9uakp",
      "publish_time": "2026-04-16 16:12:08",
      "heat": "1",
      "type": "公社热帖",
      "crawl_time": "2026-04-16 18:43:52"
    },
    {
      "rank": "131",
      "title": "【申万计算机】聚水潭202604：低估值电商ERP领军，AI核心受益标的",
      "link": "https://www.jiuyangongshe.com/a/115rgybjvz9",
      "publish_time": "2026-04-16 16:50:01",
      "heat": "1",
      "type": "公社热帖",
      "crawl_time": "2026-04-16 18:43:52"
    },
    {
      "rank": "132",
      "title": "【申万轻工&计算机】群核科技：4.17日港股正式上市",
      "link": "https://www.jiuyangongshe.com/a/3xzldhty956",
      "publish_time": "2026-04-16 16:45:35",
      "heat": "1",
      "type": "公社热帖",
      "crawl_time": "2026-04-16 18:43:52"
    },
    {
      "rank": "133",
      "title": "【长江另类策略-04/16】成长强势反弹，创业板成长动量涨近4%",
      "link": "https://www.jiuyangongshe.com/a/2z1n42hrj50",
      "publish_time": "2026-04-16 17:07:07",
      "heat": "1",
      "type": "公社热帖",
      "crawl_time": "2026-04-16 18:43:52"
    },
    {
      "rank": "134",
      "title": "【长江轻工】金富科技：完成并购卓晖金属、联益热能，稀缺液冷供应链龙头",
      "link": "https://www.jiuyangongshe.com/a/4efkezvw3nw",
      "publish_time": "2026-04-16 15:09:02",
      "heat": "1",
      "type": "公社热帖",
      "crawl_time": "2026-04-16 18:43:52"
    },
    {
      "rank": "135",
      "title": "业绩爆发|锂矿行业投资可行性分析",
      "link": "https://www.jiuyangongshe.com/a/4efkyp4b8as",
      "publish_time": "2026-04-16 22:45:00",
      "heat": "1",
      "type": "公社热帖",
      "crawl_time": "2026-04-16 18:43:52"
    },
    {
      "rank": "136",
      "title": "狮头股份：消费＋科技＋新能源＋房地产（基本面预期差小票）",
      "link": "https://www.jiuyangongshe.com/a/3xzm1e58e7b",
      "publish_time": "2026-04-17 02:07:01",
      "heat": "0",
      "type": "公社热帖",
      "crawl_time": "2026-04-16 18:43:52"
    }
  ],
  "财经日历": [
    {
      "rank": "",
      "title": "台积电2026年第一季度财报电话会议将于4月16日北京时间下午2点/美国东部时间下午2点举行",
      "link": "",
      "publish_time": "2026-04-16",
      "heat": "",
      "type": "财经日历",
      "crawl_time": "2026-04-16 18:43:55"
    },
    {
      "rank": "",
      "title": "商务部定于4月16日下午3时举行新闻发布会，介绍近期商务领域重点工作有关情况",
      "link": "",
      "publish_time": "2026-04-16",
      "heat": "",
      "type": "财经日历",
      "crawl_time": "2026-04-16 18:43:55"
    },
    {
      "rank": "",
      "title": "国家统计局4月16日将发布一季度国民经济运行数据",
      "link": "",
      "publish_time": "2026-04-16",
      "heat": "",
      "type": "财经日历",
      "crawl_time": "2026-04-16 18:43:55"
    },
    {
      "rank": "",
      "title": "中国城镇供水排水协会2026年会暨城镇水务技术与产品展会(简称“水协年会”)，将于4月16日-18日在深圳召开",
      "link": "",
      "publish_time": "2026-04-16",
      "heat": "",
      "type": "财经日历",
      "crawl_time": "2026-04-16 18:43:55"
    },
    {
      "rank": "",
      "title": "第十六届北京国际电影节将于4月16日至4月25日举办",
      "link": "",
      "publish_time": "2026-04-16",
      "heat": "",
      "type": "财经日历",
      "crawl_time": "2026-04-16 18:43:55"
    },
    {
      "rank": "",
      "title": "2026年4月16日，由CDCC主办、腾讯数据中心战略协办的第四届数据中心液冷技术大会将在深圳盛大召开",
      "link": "",
      "publish_time": "2026-04-16",
      "heat": "",
      "type": "财经日历",
      "crawl_time": "2026-04-16 18:43:55"
    },
    {
      "rank": "",
      "title": "3月商品住宅销售价格指数月度报告将于4月16日9:30公布(70个大中城市住宅销售价格)",
      "link": "",
      "publish_time": "2026-04-16",
      "heat": "",
      "type": "财经日历",
      "crawl_time": "2026-04-16 18:43:55"
    },
    {
      "rank": "",
      "title": "零跑D19上市发布会将于4月16日举行",
      "link": "",
      "publish_time": "2026-04-16",
      "heat": "",
      "type": "财经日历",
      "crawl_time": "2026-04-16 18:43:55"
    },
    {
      "rank": "",
      "title": "第十四届全国磁约束聚变理论与模拟会议将于4月16-19日举行",
      "link": "",
      "publish_time": "2026-04-16",
      "heat": "",
      "type": "财经日历",
      "crawl_time": "2026-04-16 18:43:55"
    },
    {
      "rank": "",
      "title": "恺英网络自研自发的《三国:天下归心》手游将于2026年4月16日全平台公测，PC、安卓、iOS同步上线",
      "link": "",
      "publish_time": "2026-04-16",
      "heat": "",
      "type": "财经日历",
      "crawl_time": "2026-04-16 18:43:55"
    },
    {
      "rank": "",
      "title": "一季度国民经济运行情况发布会将于4月16日10:00发布，在发布国民经济运行情况新闻发布稿的同时，分别发布工业生产、能源生产、固定资产投资、房地产开发投资和销售、社会消费品零售总额等数据",
      "link": "",
      "publish_time": "2026-04-16",
      "heat": "",
      "type": "财经日历",
      "crawl_time": "2026-04-16 18:43:55"
    },
    {
      "rank": "",
      "title": "2026第三届数据要素创新发展大会将于4月16日至17日举办",
      "link": "",
      "publish_time": "2026-04-16",
      "heat": "",
      "type": "财经日历",
      "crawl_time": "2026-04-16 18:43:55"
    },
    {
      "rank": "",
      "title": "第四届数据中心液冷技术大会将于4月16日在深圳召开",
      "link": "",
      "publish_time": "2026-04-16",
      "heat": "",
      "type": "财经日历",
      "crawl_time": "2026-04-16 18:43:55"
    },
    {
      "rank": "",
      "title": "2026年4月16日-18日，张江药谷国际创新大会·先进疗法论坛暨2026上海干细胞产业大会将于张江科学会堂盛大启幕",
      "link": "",
      "publish_time": "2026-04-16",
      "heat": "",
      "type": "财经日历",
      "crawl_time": "2026-04-16 18:43:55"
    },
    {
      "rank": "",
      "title": "智元合作伙伴大会将于4月17日在上海举办",
      "link": "",
      "publish_time": "2026-04-17",
      "heat": "",
      "type": "财经日历",
      "crawl_time": "2026-04-16 18:43:55"
    },
    {
      "rank": "",
      "title": "马斯克旗下通讯软件XChat预计4月17日上架苹果App Store",
      "link": "",
      "publish_time": "2026-04-17",
      "heat": "",
      "type": "财经日历",
      "crawl_time": "2026-04-16 18:43:55"
    },
    {
      "rank": "",
      "title": "美国癌症研究协会（AACR）第117届年会将于4月17日至4月22日在美国举行",
      "link": "",
      "publish_time": "2026-04-17",
      "heat": "",
      "type": "财经日历",
      "crawl_time": "2026-04-16 18:43:55"
    },
    {
      "rank": "",
      "title": "群核科技计划4月17日在港交所挂牌，将成为“全球空间智能第一股”，亦是“杭州六小龙”中首家上市公司",
      "link": "",
      "publish_time": "2026-04-17",
      "heat": "",
      "type": "财经日历",
      "crawl_time": "2026-04-16 18:43:55"
    },
    {
      "rank": "",
      "title": "群核科技计划于4月17日正式以“00068”为股票代码在港交所挂牌上市",
      "link": "",
      "publish_time": "2026-04-17",
      "heat": "",
      "type": "财经日历",
      "crawl_time": "2026-04-16 18:43:55"
    },
    {
      "rank": "",
      "title": "AACR(美国癌症研究协会年会)将于4月17-22日举行，中国创新药全球集中亮相，大量ADC、双抗、小分子公布临床数据",
      "link": "",
      "publish_time": "2026-04-17",
      "heat": "",
      "type": "财经日历",
      "crawl_time": "2026-04-16 18:43:55"
    },
    {
      "rank": "",
      "title": "4月17日9:30一季度主要行业增加值初步核算报告(经济数据)",
      "link": "",
      "publish_time": "2026-04-17",
      "heat": "",
      "type": "财经日历",
      "crawl_time": "2026-04-16 18:43:55"
    },
    {
      "rank": "",
      "title": "2026智元全球合作伙伴大会共启具身智能生产力新时代将于4月17日举行",
      "link": "",
      "publish_time": "2026-04-17",
      "heat": "",
      "type": "财经日历",
      "crawl_time": "2026-04-16 18:43:55"
    },
    {
      "rank": "",
      "title": "股指期货交割日",
      "link": "",
      "publish_time": "2026-04-17",
      "heat": "",
      "type": "财经日历",
      "crawl_time": "2026-04-16 18:43:55"
    },
    {
      "rank": "",
      "title": "2026中国人形机器人生态大会将于4月17日至19日在上海举办",
      "link": "",
      "publish_time": "2026-04-17",
      "heat": "",
      "type": "财经日历",
      "crawl_time": "2026-04-16 18:43:55"
    },
    {
      "rank": "",
      "title": "2026年可持续农业与环境国际研讨会(SAE2026)将于2026年4月17-19日在中国西安举行",
      "link": "",
      "publish_time": "2026-04-17",
      "heat": "",
      "type": "财经日历",
      "crawl_time": "2026-04-16 18:43:55"
    },
    {
      "rank": "",
      "title": "2026山东省齐鲁足球超级联赛将于4月18日开幕",
      "link": "",
      "publish_time": "2026-04-18",
      "heat": "",
      "type": "财经日历",
      "crawl_time": "2026-04-16 18:43:55"
    },
    {
      "rank": "",
      "title": "百度智能发布的调价公告，AI算力相关产品上调幅度约为5%-30%，并行文件存储上调幅度约为30%，自4月18日起执行",
      "link": "",
      "publish_time": "2026-04-18",
      "heat": "",
      "type": "财经日历",
      "crawl_time": "2026-04-16 18:43:55"
    },
    {
      "rank": "",
      "title": "2026第六届雷达未来大会定于2026年4月18日-20日召开",
      "link": "",
      "publish_time": "2026-04-18",
      "heat": "",
      "type": "财经日历",
      "crawl_time": "2026-04-16 18:43:55"
    },
    {
      "rank": "",
      "title": "2026北京亦庄半程马拉松暨人形机器人半程马拉松将于4月19日举办",
      "link": "",
      "publish_time": "2026-04-19",
      "heat": "",
      "type": "财经日历",
      "crawl_time": "2026-04-16 18:43:55"
    },
    {
      "rank": "",
      "title": "北京亦庄正式宣布将于2026年4月19日举办人形机器人半程马拉松和北京亦庄半程马拉松，赛事报名通道正式开启",
      "link": "",
      "publish_time": "2026-04-19",
      "heat": "",
      "type": "财经日历",
      "crawl_time": "2026-04-16 18:43:55"
    },
    {
      "rank": "",
      "title": "4月19日长征十号乙火箭发射",
      "link": "",
      "publish_time": "2026-04-19",
      "heat": "",
      "type": "财经日历",
      "crawl_time": "2026-04-16 18:43:55"
    },
    {
      "rank": "",
      "title": "全球首个自动驾驶移动空间路线4月20日试运营",
      "link": "",
      "publish_time": "2026-04-20",
      "heat": "",
      "type": "财经日历",
      "crawl_time": "2026-04-16 18:43:55"
    },
    {
      "rank": "",
      "title": "华为大阔折手机华为Pura X Max新机将于4月20日正式发布",
      "link": "",
      "publish_time": "2026-04-20",
      "heat": "",
      "type": "财经日历",
      "crawl_time": "2026-04-16 18:43:55"
    },
    {
      "rank": "",
      "title": "大疆Osmo Pocket4即将全球发布，市场预计为4月20日发布(大疆pocket3用一片模造玻璃，pocket4用3片，零部件价值大幅提升)",
      "link": "",
      "publish_time": "2026-04-20",
      "heat": "",
      "type": "财经日历",
      "crawl_time": "2026-04-16 18:43:55"
    },
    {
      "rank": "",
      "title": "一年期/五年期贷款市场报价利率(LPR)将于4月20日公布",
      "link": "",
      "publish_time": "2026-04-20",
      "heat": "",
      "type": "财经日历",
      "crawl_time": "2026-04-16 18:43:55"
    },
    {
      "rank": "",
      "title": "4月20-23日，2026香港Web3嘉年华将于香港会议展览中心盛大启幕",
      "link": "",
      "publish_time": "2026-04-20",
      "heat": "",
      "type": "财经日历",
      "crawl_time": "2026-04-16 18:43:55"
    },
    {
      "rank": "",
      "title": "美国海关与边境保护局(CBP)表示，寻求关税退款的进口商将可从4月20日开始提交申请",
      "link": "",
      "publish_time": "2026-04-20",
      "heat": "",
      "type": "财经日历",
      "crawl_time": "2026-04-16 18:43:55"
    },
    {
      "rank": "",
      "title": "华为Pura系列及全场景新品发布会将于4月20日14:30召开，Pura90系列、AI眼镜、阔折叠或将发布",
      "link": "",
      "publish_time": "2026-04-20",
      "heat": "",
      "type": "财经日历",
      "crawl_time": "2026-04-16 18:43:55"
    },
    {
      "rank": "",
      "title": "第十四届中国数控机床展览会将于4月21日至25日在上海举行",
      "link": "",
      "publish_time": "2026-04-21",
      "heat": "",
      "type": "财经日历",
      "crawl_time": "2026-04-16 18:43:55"
    },
    {
      "rank": "",
      "title": "速腾聚创将于4月21日举办技术开放日:车载激光雷达或迎芯片级突破，双轮战略加速兑现",
      "link": "",
      "publish_time": "2026-04-21",
      "heat": "",
      "type": "财经日历",
      "crawl_time": "2026-04-16 18:43:55"
    },
    {
      "rank": "",
      "title": "2026年国际生物样本库大会将于4月21-23日在深圳举行",
      "link": "",
      "publish_time": "2026-04-21",
      "heat": "",
      "type": "财经日历",
      "crawl_time": "2026-04-16 18:43:55"
    },
    {
      "rank": "",
      "title": "第三十八届中国国际塑料橡胶工业展览会(CHINAPLAS橡塑展)将于2026年4月21-24日在上海举办，，以“变革·协作·共塑可持续”为主题",
      "link": "",
      "publish_time": "2026-04-21",
      "heat": "",
      "type": "财经日历",
      "crawl_time": "2026-04-16 18:43:55"
    },
    {
      "rank": "",
      "title": "国内成品油将在4月21日24时迎来年内第八轮调整",
      "link": "",
      "publish_time": "2026-04-21",
      "heat": "",
      "type": "财经日历",
      "crawl_time": "2026-04-16 18:43:55"
    },
    {
      "rank": "",
      "title": "俄国限制硝酸铵出口直至4月21日",
      "link": "",
      "publish_time": "2026-04-21",
      "heat": "",
      "type": "财经日历",
      "crawl_time": "2026-04-16 18:43:55"
    },
    {
      "rank": "",
      "title": "2026全球6G技术与产业生态大会将于4月21日至23日在南京举行",
      "link": "",
      "publish_time": "2026-04-21",
      "heat": "",
      "type": "财经日历",
      "crawl_time": "2026-04-16 18:43:55"
    },
    {
      "rank": "",
      "title": "新一代旅拍神器OPPOFindx9sPro，哈苏双2亿，世界和我都清晰，4月21日19:00全球首发",
      "link": "",
      "publish_time": "2026-04-21",
      "heat": "",
      "type": "财经日历",
      "crawl_time": "2026-04-16 18:43:55"
    },
    {
      "rank": "",
      "title": "第六届亚洲沙滩运动会将于4月22日至30日在中国海南省三亚。市举行，是亚洲规模最大的沙滩运动盛会",
      "link": "",
      "publish_time": "2026-04-22",
      "heat": "",
      "type": "财经日历",
      "crawl_time": "2026-04-16 18:43:55"
    },
    {
      "rank": "",
      "title": "第一届催化剂技术创新应用发展大会将于4月22-23日举办",
      "link": "",
      "publish_time": "2026-04-22",
      "heat": "",
      "type": "财经日历",
      "crawl_time": "2026-04-16 18:43:55"
    },
    {
      "rank": "",
      "title": "谷歌将于4月22-24日Google Cloud Next大会",
      "link": "",
      "publish_time": "2026-04-22",
      "heat": "",
      "type": "财经日历",
      "crawl_time": "2026-04-16 18:43:55"
    },
    {
      "rank": "",
      "title": "2026第二十届消费经济发展论坛(春季)将于4月22日在北京举办",
      "link": "",
      "publish_time": "2026-04-22",
      "heat": "",
      "type": "财经日历",
      "crawl_time": "2026-04-16 18:43:55"
    },
    {
      "rank": "",
      "title": "2026（第五届）半导体生态创新大会将于4月22日至23日在上海举办",
      "link": "",
      "publish_time": "2026-04-22",
      "heat": "",
      "type": "财经日历",
      "crawl_time": "2026-04-16 18:43:55"
    },
    {
      "rank": "",
      "title": "第32届中国国际广播电视信息网络展览会将于4月22-25日在北京举办",
      "link": "",
      "publish_time": "2026-04-22",
      "heat": "",
      "type": "财经日历",
      "crawl_time": "2026-04-16 18:43:55"
    },
    {
      "rank": "",
      "title": "华为乾崑技术大会将在4月23日19:00举行，发布HUAWEI ADS 5、HarmonySpace 6和更多创新技术",
      "link": "",
      "publish_time": "2026-04-23",
      "heat": "",
      "type": "财经日历",
      "crawl_time": "2026-04-16 18:43:55"
    },
    {
      "rank": "",
      "title": "2026(第四届)通用航空与无人机发展大会将于4月23-24日在北京举办",
      "link": "",
      "publish_time": "2026-04-23",
      "heat": "",
      "type": "财经日历",
      "crawl_time": "2026-04-16 18:43:55"
    },
    {
      "rank": "",
      "title": "2026第35届中国国际健康产业博览会(CIHIE 健博会)将于4月23一25日在北京举行",
      "link": "",
      "publish_time": "2026-04-23",
      "heat": "",
      "type": "财经日历",
      "crawl_time": "2026-04-16 18:43:55"
    },
    {
      "rank": "",
      "title": "华为鸿蒙HarmonyOS6开放世界RPG游戏《异环》全平台公测定档4月23日",
      "link": "",
      "publish_time": "2026-04-23",
      "heat": "",
      "type": "财经日历",
      "crawl_time": "2026-04-16 18:43:55"
    },
    {
      "rank": "",
      "title": "2026空天地一体化智能巡检大会暨第11届全国无人机电力应用技术高峰论坛将于4月23-24日在山东青岛召开",
      "link": "",
      "publish_time": "2026-04-23",
      "heat": "",
      "type": "财经日历",
      "crawl_time": "2026-04-16 18:43:55"
    },
    {
      "rank": "",
      "title": "2026(第五届)中国国际矿业投资与发展高峰会议定于2026年4月23日一25日在北京西直门宾馆举办",
      "link": "",
      "publish_time": "2026-04-23",
      "heat": "",
      "type": "财经日历",
      "crawl_time": "2026-04-16 18:43:55"
    },
    {
      "rank": "",
      "title": "第三届能源新质生产力发展战略研讨会暨第四届能源经济学术研讨会定于2026年4月24日至26日在西安市举办",
      "link": "",
      "publish_time": "2026-04-24",
      "heat": "",
      "type": "财经日历",
      "crawl_time": "2026-04-16 18:43:55"
    },
    {
      "rank": "",
      "title": "2026(第十九届)北京国际汽车展览会将于4月24日-5月3日在北京举行",
      "link": "",
      "publish_time": "2026-04-24",
      "heat": "",
      "type": "财经日历",
      "crawl_time": "2026-04-16 18:43:55"
    },
    {
      "rank": "",
      "title": "4月24日北京车展江淮MPV车型亮相，2026年三季度江淮尊界MPV+S900发布",
      "link": "",
      "publish_time": "2026-04-24",
      "heat": "",
      "type": "财经日历",
      "crawl_time": "2026-04-16 18:43:55"
    },
    {
      "rank": "",
      "title": "第九届数字中国建设峰会将于4月29日至4月30日在福建举办",
      "link": "",
      "publish_time": "2026-04-29",
      "heat": "",
      "type": "财经日历",
      "crawl_time": "2026-04-16 18:43:55"
    },
    {
      "rank": "",
      "title": "美联储FOMC公布利率决议。",
      "link": "",
      "publish_time": "2026-04-30",
      "heat": "",
      "type": "财经日历",
      "crawl_time": "2026-04-16 18:43:55"
    },
    {
      "rank": "",
      "title": "美联储主席鲍威尔召开货币政策新闻发布会。[同传]",
      "link": "",
      "publish_time": "2026-04-30",
      "heat": "",
      "type": "财经日历",
      "crawl_time": "2026-04-16 18:43:55"
    },
    {
      "rank": "",
      "title": "《民用无人驾驶航空器实名登记和激活要求》（GB 46761—2025）和《民用无人驾驶航空器系统运行识别规范》（GB 46750—2025）两项强制性国家标准将于5月1日起正式实施",
      "link": "",
      "publish_time": "2026-05-01",
      "heat": "",
      "type": "财经日历",
      "crawl_time": "2026-04-16 18:43:55"
    }
  ]
}